local_qwen3b_part029/__init__.py
local_qwen3b_part029/qwen2.5-3b-instruct-q5_k_m.gguf.part_029
local_qwen3b_part029-0.0.1.dist-info/METADATA
local_qwen3b_part029-0.0.1.dist-info/WHEEL
local_qwen3b_part029-0.0.1.dist-info/top_level.txt
local_qwen3b_part029-0.0.1.dist-info/RECORD
